<?xml version="1.0" encoding="utf-8"?>
<DDC 
  CLASS="ENT" 
  KEY="Z_116_DAILY_LIMIT_HIGH_LOANS" 
  MODE="O" 
  xmlns:LINK="ddc:link" 
  xmlns:CFG="ddc:cfg" 
  HASH="86E2DD337B9D7B9A97B505B3E8BBFB65">
  <ENT 
    CODE="Z_116_DAILY_LIMIT_HIGH_LOANS" 
    ARCFL="0" 
    CLTYPE="E" 
    GENSTATUS="F" 
    LONGNAME="Z_116_DAILY_LIMIT_HIGH_LOANS" 
    NAME="Z_116_DAILY_LIMIT_HIGH_LOANS" 
    PROTECT="N" 
    REFRESHFL="0" 
    SHORTNAME="DLHL">
    <LINK:MOD 
      CODE="LN"/>
    <ENTCATR 
      ATTR="DORD" 
      ATTRTYP="F" 
      ID="5" 
      LONGNAME="dord" 
      MANDAT="H" 
      MLFL="0" 
      NAME="dord1" 
      NPP="1" 
      PROTECT="N" 
      SHORTNAME="*" 
      STATFL="1" 
      TYPEDEF="DATE"/>
    <ENTCATR 
      ATTR="FACT_COUNT" 
      ATTRTYP="F" 
      ID="8" 
      LONGNAME="fact_count" 
      MANDAT="H" 
      MLFL="0" 
      NAME="fact_count1" 
      NPP="4" 
      PROTECT="N" 
      SHORTNAME="*" 
      STATFL="0" 
      TYPEDEF="NUMBER"/>
    <ENTCATR 
      ATTR="LIMIT_COUNT" 
      ATTRTYP="F" 
      ID="7" 
      LONGNAME="limit_count" 
      MANDAT="H" 
      MLFL="0" 
      NAME="limit_count1" 
      NPP="3" 
      PROTECT="N" 
      SHORTNAME="*" 
      STATFL="0" 
      TYPEDEF="NUMBER"/>
    <ENTCATR 
      ATTR="REQ_TYPE" 
      ATTRTYP="F" 
      ID="6" 
      LONGNAME="req_type" 
      MANDAT="H" 
      MLFL="0" 
      NAME="req_type1" 
      NPP="2" 
      PROTECT="N" 
      SHORTNAME="*" 
      STATFL="1" 
      TYPEDEF="VARCHAR2(50)"/>
    <ENTATR 
      GENMODE="T" 
      ID="63795885" 
      MANUALFL="1">
      <LINK:CSYS 
        SYSTEM="BS"/>
      <ENTPKEY 
        CKEY="%_PK" 
        FOREIGNFL="0" 
        GENCNSFL="1" 
        GENIDXFL="1" 
        PRIMARYFL="1" 
        PROTECT="N" 
        UNIQUEFL="0">
        <ENTPKEYFLD 
          NPP="1">
          <LINK:ENT 
            CODE="Z_116_DAILY_LIMIT_HIGH_LOANS" 
            ATTR="DORD"/>
        </ENTPKEYFLD>
        <ENTPKEYFLD 
          NPP="2">
          <LINK:ENT 
            CODE="Z_116_DAILY_LIMIT_HIGH_LOANS" 
            ATTR="REQ_TYPE"/>
        </ENTPKEYFLD>
      </ENTPKEY>
    </ENTATR>
    <ENTTXT>
      <LOB_FIELD 
        NAME="TEXT">
        <![CDATA[]]>
      </LOB_FIELD>
    </ENTTXT>
  </ENT>
</DDC>
